asyncwebostv/__init__.py
asyncwebostv/client.py
asyncwebostv/connection.py
asyncwebostv/controls.py
asyncwebostv/discovery.py
asyncwebostv/model.py
asyncwebostv/py.typed
asyncwebostv/secure_connection.py
asyncwebostv-0.2.7.dist-info/licenses/LICENSE
asyncwebostv-0.2.7.dist-info/METADATA
asyncwebostv-0.2.7.dist-info/WHEEL
asyncwebostv-0.2.7.dist-info/top_level.txt
asyncwebostv-0.2.7.dist-info/RECORD
