Metadata-Version: 2.4
Name: asyncwebostv
Version: 0.2.7
Summary: Asynchronous client library for LG WebOS TVs
Author-email: AsyncWebOSTV Team <your-email@example.com>
License-Expression: MIT
Classifier: Programming Language :: Python :: 3
Classifier: Operating System :: OS Independent
Classifier: Development Status :: 3 - Alpha
Classifier: Typing :: Typed
Requires-Python: >=3.11
License-File: LICENSE
Requires-Dist: aiohttp>=3.8.0
Requires-Dist: websockets>=15.0.1
Requires-Dist: aiofiles>=0.8.0
Requires-Dist: typing_extensions>=4.0.0
Requires-Dist: aiohttp-sse-client>=0.2.0
Requires-Dist: aiohttp-socks>=0.7.0
Requires-Dist: build>=1.2.2.post1
Requires-Dist: twine>=6.1.0
Provides-Extra: dev
Requires-Dist: pytest>=7.0.0; extra == "dev"
Requires-Dist: pytest-asyncio>=0.18.0; extra == "dev"
Requires-Dist: black>=22.0.0; extra == "dev"
Requires-Dist: isort>=5.0.0; extra == "dev"
Requires-Dist: mypy>=0.900; extra == "dev"
Dynamic: license-file
